odoo10_addon_partner_aging-10.0.1.0.0-py2.7-nspkg.pth
odoo/addons/partner_aging/README.rst
odoo/addons/partner_aging/__init__.py
odoo/addons/partner_aging/__manifest__.py
odoo/addons/partner_aging/security/ir.model.access.csv
odoo/addons/partner_aging/static/description/icon.png
odoo/addons/partner_aging/tests/__init__.py
odoo/addons/partner_aging/tests/test_partner_aging.py
odoo/addons/partner_aging/wizards/__init__.py
odoo/addons/partner_aging/wizards/res_partner_aging_customer.py
odoo/addons/partner_aging/wizards/res_partner_aging_customer.xml
odoo/addons/partner_aging/wizards/res_partner_aging_date.py
odoo/addons/partner_aging/wizards/res_partner_aging_supplier.py
odoo/addons/partner_aging/wizards/res_partner_aging_supplier.xml
odoo10_addon_partner_aging-10.0.1.0.0.dist-info/METADATA
odoo10_addon_partner_aging-10.0.1.0.0.dist-info/RECORD
odoo10_addon_partner_aging-10.0.1.0.0.dist-info/WHEEL
odoo10_addon_partner_aging-10.0.1.0.0.dist-info/namespace_packages.txt
odoo10_addon_partner_aging-10.0.1.0.0.dist-info/top_level.txt
